watchmyups/__init__.py
watchmyups/__main__.py
watchmyups/watchmyups.py
watchmyups-1.0.0.dist-info/licenses/LICENSE
watchmyups-1.0.0.dist-info/METADATA
watchmyups-1.0.0.dist-info/WHEEL
watchmyups-1.0.0.dist-info/entry_points.txt
watchmyups-1.0.0.dist-info/top_level.txt
watchmyups-1.0.0.dist-info/RECORD
