Metadata-Version: 2.4
Name: watchmyups
Version: 1.0.0
Summary: A FastAPI application to expose UPS data via NUT (Network UPS Tools)
Author: Murat EFE
License:                     GNU GENERAL PUBLIC LICENSE
Project-URL: Homepage, https://github.com/murratefe/watchmyups
Project-URL: Repository, https://github.com/murratefe/watchmyups
Project-URL: Issues, https://github.com/murratefe/watchmyups/issues
Keywords: ups,nut,fastapi,monitoring,watchmyups,nut2,power,powerloss,api
Classifier: Programming Language :: Python :: 3.12
Classifier: License :: OSI Approved :: GNU General Public License v3 (GPLv3)
Classifier: Operating System :: OS Independent
Requires-Python: >=3.12
License-File: LICENSE
Requires-Dist: fastapi==0.122.0
Requires-Dist: nut2==2.1.1
Requires-Dist: pydantic==2.12.5
Requires-Dist: uvicorn==0.38.0
Dynamic: license-file
